[
  {
    "Item Name": "AVOCADO 240ml",
    "Category": "Cane Blend",
    "MRP": 70,
    "Barcode": "CFRST01",
    "Tax type": "y",
    "Tax percentage": 12
  },
  {
    "Item Name": "BLACK SALTED 240ml",
    "Category": "Cane Blend",
    "MRP": 35,
    "Barcode": "CFRST02",
    "Tax type": "y",
    "Tax percentage": 12
  },
  {
    "Item Name": "BLUEBERRY 240ml",
    "Category": "Cane Blend",
    "MRP": 70,
    "Barcode": "CFRST03",
    "Tax type": "y",
    "Tax percentage": 12
  },
  {
    "Item Name": "COFFEE 240ml",
    "Category": "Cane Blend",
    "MRP": 60,
    "Barcode": "CFRST04",
    "Tax type": "y",
    "Tax percentage": 12
  },
  {
    "Item Name": "DRAGON FRUIT 240ml",
    "Category": "Cane Blend",
    "MRP": 50,
    "Barcode": "CFRST05",
    "Tax type": "y",
    "Tax percentage": 12
  },
  {
    "Item Name": "FIG 240ml",
    "Category": "Cane Blend",
    "MRP": 50,
    "Barcode": "CFRST06",
    "Tax type": "y",
    "Tax percentage": 12
  },
  {
    "Item Name": "GINGER 240ml",
    "Category": "Cane Blend",
    "MRP": 35,
    "Barcode": "CFRST07",
    "Tax type": "y",
    "Tax percentage": 12
  },
  {
    "Item Name": "GOOSEBERRY 240ml",
    "Category": "Cane Blend",
    "MRP": 40,
    "Barcode": "CFRST08",
    "Tax type": "y",
    "Tax percentage": 12
  },
  {
    "Item Name": "GRAPES 240ml",
    "Category": "Cane Blend",
    "MRP": 50,
    "Barcode": "CFRST09",
    "Tax type": "y",
    "Tax percentage": 12
  },
  {
    "Item Name": "GUAVA 240ml",
    "Category": "Cane Blend",
    "MRP": 50,
    "Barcode": "CFRST10",
    "Tax type": "y",
    "Tax percentage": 12
  },
  {
    "Item Name": "ICE APPLE 240ml",
    "Category": "Cane Blend",
    "MRP": 60,
    "Barcode": "CFRST11",
    "Tax type": "y",
    "Tax percentage": 12
  },
  {
    "Item Name": "JACKFRUIT 240ml",
    "Category": "Cane Blend",
    "MRP": 50,
    "Barcode": "CFRST12",
    "Tax type": "y",
    "Tax percentage": 12
  },
  {
    "Item Name": "JALJEERA 240ml",
    "Category": "Cane Blend",
    "MRP": 35,
    "Barcode": "CFRST13",
    "Tax type": "y",
    "Tax percentage": 12
  },
  {
    "Item Name": "JAMUN 240ml",
    "Category": "Cane Blend",
    "MRP": 60,
    "Barcode": "CFRST14",
    "Tax type": "y",
    "Tax percentage": 12
  },
  {
    "Item Name": "JUSTCANE (PLAIN) 240ml",
    "Category": "Cane Blend",
    "MRP": 30,
    "Barcode": "CFRST15",
    "Tax type": "y",
    "Tax percentage": 12
  },
  {
    "Item Name": "LEMON 240ml",
    "Category": "Cane Blend",
    "MRP": 30,
    "Barcode": "CFRST16",
    "Tax type": "y",
    "Tax percentage": 12
  },
  {
    "Item Name": "LEMON & GINGER 240ml",
    "Category": "Cane Blend",
    "MRP": 35,
    "Barcode": "CFRST17",
    "Tax type": "y",
    "Tax percentage": 12
  },
  {
    "Item Name": "MINT 240ml",
    "Category": "Cane Blend",
    "MRP": 35,
    "Barcode": "CFRST18",
    "Tax type": "y",
    "Tax percentage": 12
  },
  {
    "Item Name": "MINT & LEMON 240ml",
    "Category": "Cane Blend",
    "MRP": 40,
    "Barcode": "CFRST19",
    "Tax type": "y",
    "Tax percentage": 12
  },
  {
    "Item Name": "MINT, LEMON & GINGER 240ml",
    "Category": "Cane Blend",
    "MRP": 40,
    "Barcode": "CFRST20",
    "Tax type": "y",
    "Tax percentage": 12
  },
  {
    "Item Name": "MOSAMBI 240ml",
    "Category": "Cane Blend",
    "MRP": 50,
    "Barcode": "CFRST21",
    "Tax type": "y",
    "Tax percentage": 12
  },
  {
    "Item Name": "MUSKMELON 240ml",
    "Category": "Cane Blend",
    "MRP": 50,
    "Barcode": "CFRST22",
    "Tax type": "y",
    "Tax percentage": 12
  },
  {
    "Item Name": "ORANGE 240ml",
    "Category": "Cane Blend",
    "MRP": 50,
    "Barcode": "CFRST23",
    "Tax type": "y",
    "Tax percentage": 12
  },
  {
    "Item Name": "PINEAPPLE 240ml",
    "Category": "Cane Blend",
    "MRP": 50,
    "Barcode": "CFRST24",
    "Tax type": "y",
    "Tax percentage": 12
  },
  {
    "Item Name": "POMEGRANATE 240ml",
    "Category": "Cane Blend",
    "MRP": 60,
    "Barcode": "CFRST25",
    "Tax type": "y",
    "Tax percentage": 12
  },
  {
    "Item Name": "STRAWBERRY 240ml",
    "Category": "Cane Blend",
    "MRP": 70,
    "Barcode": "CFRST26",
    "Tax type": "y",
    "Tax percentage": 12
  },
  {
    "Item Name": "WATERMELON 240ml",
    "Category": "Cane Blend",
    "MRP": 40,
    "Barcode": "CFRST27",
    "Tax type": "y",
    "Tax percentage": 12
  },
  {
    "Item Name": "AVOCADO 500 ml",
    "Category": "Cane Blend",
    "MRP": 140,
    "Barcode": "CFRST28",
    "Tax type": "y",
    "Tax percentage": 12
  },
  {
    "Item Name": "BLACK SALTED 500 ml",
    "Category": "Cane Blend",
    "MRP": 70,
    "Barcode": "CFRST29",
    "Tax type": "y",
    "Tax percentage": 12
  },
  {
    "Item Name": "BLUEBERRY 500 ml",
    "Category": "Cane Blend",
    "MRP": 140,
    "Barcode": "CFRST30",
    "Tax type": "y",
    "Tax percentage": 12
  },
  {
    "Item Name": "COFFEE 500 ml",
    "Category": "Cane Blend",
    "MRP": 120,
    "Barcode": "CFRST31",
    "Tax type": "y",
    "Tax percentage": 12
  },
  {
    "Item Name": "DRAGON FRUIT 500 ml",
    "Category": "Cane Blend",
    "MRP": 100,
    "Barcode": "CFRST32",
    "Tax type": "y",
    "Tax percentage": 12
  },
  {
    "Item Name": "FIG 500 ml",
    "Category": "Cane Blend",
    "MRP": 100,
    "Barcode": "CFRST33",
    "Tax type": "y",
    "Tax percentage": 12
  },
  {
    "Item Name": "GINGER 500 ml",
    "Category": "Cane Blend",
    "MRP": 70,
    "Barcode": "CFRST34",
    "Tax type": "y",
    "Tax percentage": 12
  },
  {
    "Item Name": "GOOSEBERRY 500 ml",
    "Category": "Cane Blend",
    "MRP": 80,
    "Barcode": "CFRST35",
    "Tax type": "y",
    "Tax percentage": 12
  },
  {
    "Item Name": "GRAPES 500 ml",
    "Category": "Cane Blend",
    "MRP": 100,
    "Barcode": "CFRST36",
    "Tax type": "y",
    "Tax percentage": 12
  },
  {
    "Item Name": "GUAVA 500 ml",
    "Category": "Cane Blend",
    "MRP": 100,
    "Barcode": "CFRST37",
    "Tax type": "y",
    "Tax percentage": 12
  },
  {
    "Item Name": "ICE APPLE 500 ml",
    "Category": "Cane Blend",
    "MRP": 120,
    "Barcode": "CFRST38",
    "Tax type": "y",
    "Tax percentage": 12
  },
  {
    "Item Name": "JACKFRUIT 500 ml",
    "Category": "Cane Blend",
    "MRP": 100,
    "Barcode": "CFRST39",
    "Tax type": "y",
    "Tax percentage": 12
  },
  {
    "Item Name": "JALJEERA 500 ml",
    "Category": "Cane Blend",
    "MRP": 70,
    "Barcode": "CFRST40",
    "Tax type": "y",
    "Tax percentage": 12
  },
  {
    "Item Name": "JAMUN 500 ml",
    "Category": "Cane Blend",
    "MRP": 120,
    "Barcode": "CFRST41",
    "Tax type": "y",
    "Tax percentage": 12
  },
  {
    "Item Name": "JUSTCANE (PLAIN) 500 ml",
    "Category": "Cane Blend",
    "MRP": 60,
    "Barcode": "CFRST42",
    "Tax type": "y",
    "Tax percentage": 12
  },
  {
    "Item Name": "LEMON 500 ml",
    "Category": "Cane Blend",
    "MRP": 60,
    "Barcode": "CFRST43",
    "Tax type": "y",
    "Tax percentage": 12
  },
  {
    "Item Name": "LEMON & GINGER 500 ml",
    "Category": "Cane Blend",
    "MRP": 70,
    "Barcode": "CFRST44",
    "Tax type": "y",
    "Tax percentage": 12
  },
  {
    "Item Name": "MINT 500 ml",
    "Category": "Cane Blend",
    "MRP": 70,
    "Barcode": "CFRST45",
    "Tax type": "y",
    "Tax percentage": 12
  },
  {
    "Item Name": "MINT & LEMON 500 ml",
    "Category": "Cane Blend",
    "MRP": 80,
    "Barcode": "CFRST46",
    "Tax type": "y",
    "Tax percentage": 12
  },
  {
    "Item Name": "MINT, LEMON & GINGER 500 ml",
    "Category": "Cane Blend",
    "MRP": 80,
    "Barcode": "CFRST47",
    "Tax type": "y",
    "Tax percentage": 12
  },
  {
    "Item Name": "MOSAMBI 500 ml",
    "Category": "Cane Blend",
    "MRP": 100,
    "Barcode": "CFRST48",
    "Tax type": "y",
    "Tax percentage": 12
  },
  {
    "Item Name": "MUSKMELON 500 ml",
    "Category": "Cane Blend",
    "MRP": 100,
    "Barcode": "CFRST49",
    "Tax type": "y",
    "Tax percentage": 12
  },
  {
    "Item Name": "ORANGE 500 ml",
    "Category": "Cane Blend",
    "MRP": 100,
    "Barcode": "CFRST50",
    "Tax type": "y",
    "Tax percentage": 12
  },
  {
    "Item Name": "PINEAPPLE 500 ml",
    "Category": "Cane Blend",
    "MRP": 100,
    "Barcode": "CFRST51",
    "Tax type": "y",
    "Tax percentage": 12
  },
  {
    "Item Name": "POMEGRANATE 500 ml",
    "Category": "Cane Blend",
    "MRP": 120,
    "Barcode": "CFRST52",
    "Tax type": "y",
    "Tax percentage": 12
  },
  {
    "Item Name": "STRAWBERRY 500 ml",
    "Category": "Cane Blend",
    "MRP": 140,
    "Barcode": "CFRST53",
    "Tax type": "y",
    "Tax percentage": 12
  },
  {
    "Item Name": "TENDER COCONUT 500ml",
    "Category": "Cane Blend",
    "MRP": 120,
    "Barcode": "CFRST54",
    "Tax type": "y",
    "Tax percentage": 12
  },
  {
    "Item Name": "WATERMELON 500 ml",
    "Category": "Cane Blend",
    "MRP": 80,
    "Barcode": "CFRST55",
    "Tax type": "y",
    "Tax percentage": 12
  },
  {
    "Item Name": "BLUEBERRY CANE FUSION",
    "Category": "Cane Fusion",
    "MRP": 200,
    "Barcode": "CFRST56",
    "Tax type": "y",
    "Tax percentage": 12
  },
  {
    "Item Name": "DRAGON FRUIT CANE FUSION",
    "Category": "Cane Fusion",
    "MRP": 160,
    "Barcode": "CFRST57",
    "Tax type": "y",
    "Tax percentage": 12
  },
  {
    "Item Name": "FIG CANE FUSION",
    "Category": "Cane Fusion",
    "MRP": 160,
    "Barcode": "CFRST58",
    "Tax type": "y",
    "Tax percentage": 12
  },
  {
    "Item Name": "GRAPES CANE FUSION",
    "Category": "Cane Fusion",
    "MRP": 160,
    "Barcode": "CFRST59",
    "Tax type": "y",
    "Tax percentage": 12
  },
  {
    "Item Name": "ICE APPLE CANE FUSION",
    "Category": "Cane Fusion",
    "MRP": 210,
    "Barcode": "CFRST60",
    "Tax type": "y",
    "Tax percentage": 12
  },
  {
    "Item Name": "JAMUN CANE FUSION",
    "Category": "Cane Fusion",
    "MRP": 160,
    "Barcode": "CFRST61",
    "Tax type": "y",
    "Tax percentage": 12
  },
  {
    "Item Name": "MOSAMBI CANE FUSION",
    "Category": "Cane Fusion",
    "MRP": 150,
    "Barcode": "CFRST62",
    "Tax type": "y",
    "Tax percentage": 12
  },
  {
    "Item Name": "ORANGE CANE FUSION",
    "Category": "Cane Fusion",
    "MRP": 180,
    "Barcode": "CFRST63",
    "Tax type": "y",
    "Tax percentage": 12
  },
  {
    "Item Name": "PINEAPPLE CANE FUSION",
    "Category": "Cane Fusion",
    "MRP": 160,
    "Barcode": "CFRST64",
    "Tax type": "y",
    "Tax percentage": 12
  },
  {
    "Item Name": "POMEGRANATE CANE FUSION",
    "Category": "Cane Fusion",
    "MRP": 200,
    "Barcode": "CFRST65",
    "Tax type": "y",
    "Tax percentage": 12
  },
  {
    "Item Name": "STRAWBERRY CANE FUSION",
    "Category": "Cane Fusion",
    "MRP": 200,
    "Barcode": "CFRST66",
    "Tax type": "y",
    "Tax percentage": 12
  },
  {
    "Item Name": "WATERMELON CANE FUSION",
    "Category": "Cane Fusion",
    "MRP": 160,
    "Barcode": "CFRST67",
    "Tax type": "y",
    "Tax percentage": 12
  },
  {
    "Item Name": "ALMOND & CASHEW",
    "Category": "Cane Pops",
    "MRP": 30,
    "Barcode": "CFRST68",
    "Tax type": "y",
    "Tax percentage": 12
  },
  {
    "Item Name": "AVOCADO CANESICLE",
    "Category": "Cane Pops",
    "MRP": 25,
    "Barcode": "CFRST69",
    "Tax type": "y",
    "Tax percentage": 12
  },
  {
    "Item Name": "CHOCO CHIPS CANESICLE",
    "Category": "Cane Pops",
    "MRP": 15,
    "Barcode": "CFRST70",
    "Tax type": "y",
    "Tax percentage": 12
  },
  {
    "Item Name": "COFFEE CANESICLE",
    "Category": "Cane Pops",
    "MRP": 20,
    "Barcode": "CFRST71",
    "Tax type": "y",
    "Tax percentage": 12
  },
  {
    "Item Name": "DRAGON CANESICLE",
    "Category": "Cane Pops",
    "MRP": 20,
    "Barcode": "CFRST72",
    "Tax type": "y",
    "Tax percentage": 12
  },
  {
    "Item Name": "FIG CANESICLE",
    "Category": "Cane Pops",
    "MRP": 20,
    "Barcode": "CFRST73",
    "Tax type": "y",
    "Tax percentage": 12
  },
  {
    "Item Name": "GOOSEBERRY CANESICLE",
    "Category": "Cane Pops",
    "MRP": 20,
    "Barcode": "CFRST74",
    "Tax type": "y",
    "Tax percentage": 12
  },
  {
    "Item Name": "GRAPES CANESICLE",
    "Category": "Cane Pops",
    "MRP": 20,
    "Barcode": "CFRST75",
    "Tax type": "y",
    "Tax percentage": 12
  },
  {
    "Item Name": "GUAVA CANESICLE",
    "Category": "Cane Pops",
    "MRP": 20,
    "Barcode": "CFRST76",
    "Tax type": "y",
    "Tax percentage": 12
  },
  {
    "Item Name": "JAMUN CANESICLE",
    "Category": "Cane Pops",
    "MRP": 20,
    "Barcode": "CFRST77",
    "Tax type": "y",
    "Tax percentage": 12
  },
  {
    "Item Name": "JUSTCANE CANESICLE",
    "Category": "Cane Pops",
    "MRP": 10,
    "Barcode": "CFRST78",
    "Tax type": "y",
    "Tax percentage": 12
  },
  {
    "Item Name": "LEMON & GINGER CANESICLE",
    "Category": "Cane Pops",
    "MRP": 15,
    "Barcode": "CFRST79",
    "Tax type": "y",
    "Tax percentage": 12
  },
  {
    "Item Name": "MUSKMELON CANESICLE",
    "Category": "Cane Pops",
    "MRP": 20,
    "Barcode": "CFRST80",
    "Tax type": "y",
    "Tax percentage": 12
  },
  {
    "Item Name": "ORANGE CANESICLE",
    "Category": "Cane Pops",
    "MRP": 20,
    "Barcode": "CFRST81",
    "Tax type": "y",
    "Tax percentage": 12
  },
  {
    "Item Name": "PINEAPPLE CANESICLE",
    "Category": "Cane Pops",
    "MRP": 20,
    "Barcode": "CFRST82",
    "Tax type": "y",
    "Tax percentage": 12
  },
  {
    "Item Name": "POMEGRANATE CANESICLE",
    "Category": "Cane Pops",
    "MRP": 20,
    "Barcode": "CFRST83",
    "Tax type": "y",
    "Tax percentage": 12
  },
  {
    "Item Name": "STRAWBERRY CANESICLE",
    "Category": "Cane Pops",
    "MRP": 20,
    "Barcode": "CFRST84",
    "Tax type": "y",
    "Tax percentage": 12
  },
  {
    "Item Name": "TENDER COCONUT CANESICLE",
    "Category": "Cane Pops",
    "MRP": 25,
    "Barcode": "CFRST85",
    "Tax type": "y",
    "Tax percentage": 12
  },
  {
    "Item Name": "WATERMELON CANESICLE",
    "Category": "Cane Pops",
    "MRP": 20,
    "Barcode": "CFRST86",
    "Tax type": "y",
    "Tax percentage": 12
  },
  {
    "Item Name": "WATERMELON BLAST",
    "Category": "Cane Special",
    "MRP": 350,
    "Barcode": "CFRST87",
    "Tax type": "y",
    "Tax percentage": 12
  },
  {
    "Item Name": "MUSKMELON BLAST",
    "Category": "Cane Special",
    "MRP": 130,
    "Barcode": "CFRST88",
    "Tax type": "y",
    "Tax percentage": 12
  },
  {
    "Item Name": "TENDER COCONUT 50",
    "Category": "Others",
    "MRP": 50,
    "Barcode": "CFRST89",
    "Tax type": "y",
    "Tax percentage": 12
  },
  {
    "Item Name": "TENDER COCONUT 90",
    "Category": "Others",
    "MRP": 90,
    "Barcode": "CFRST90",
    "Tax type": "y",
    "Tax percentage": 12
  },
  {
    "Item Name": "WATER BOTTLE 1 LITRE",
    "Category": "Others",
    "MRP": 20,
    "Barcode": "CFRST91",
    "Tax type": "y",
    "Tax percentage": 12
  },
  {
    "Item Name": "WATER BOTTLE 500ML",
    "Category": "Others",
    "MRP": 10,
    "Barcode": "CFRST92",
    "Tax type": "y",
    "Tax percentage": 12
  },
  {
    "Item Name": "PEANUT BARFI",
    "Category": "Others",
    "MRP": 5,
    "Barcode": "CFRST93",
    "Tax type": "y",
    "Tax percentage": 12
  },
  {
    "Item Name": "PACKAGING CHARGE",
    "Category": "Others",
    "MRP": 10,
    "Barcode": "CFRST94",
    "Tax type": "y",
    "Tax percentage": 12
  }
]